ansys/systemcoupling/core/__init__.py
ansys/systemcoupling/core/_version.py
ansys/systemcoupling/core/session.py
ansys/systemcoupling/core/syc_version.py
ansys/systemcoupling/core/adaptor/api_23_1/_add_participant.py
ansys/systemcoupling/core/adaptor/api_23_1/_clear_state.py
ansys/systemcoupling/core/adaptor/api_23_1/_solve.py
ansys/systemcoupling/core/adaptor/api_23_1/abort.py
ansys/systemcoupling/core/adaptor/api_23_1/activate_hidden.py
ansys/systemcoupling/core/adaptor/api_23_1/add_data_transfer.py
ansys/systemcoupling/core/adaptor/api_23_1/add_data_transfer_by_display_names.py
ansys/systemcoupling/core/adaptor/api_23_1/add_expression_function.py
ansys/systemcoupling/core/adaptor/api_23_1/add_interface.py
ansys/systemcoupling/core/adaptor/api_23_1/add_interface_by_display_names.py
ansys/systemcoupling/core/adaptor/api_23_1/add_named_expression.py
ansys/systemcoupling/core/adaptor/api_23_1/add_participant.py
ansys/systemcoupling/core/adaptor/api_23_1/add_reference_frame.py
ansys/systemcoupling/core/adaptor/api_23_1/add_transformation.py
ansys/systemcoupling/core/adaptor/api_23_1/analysis_control.py
ansys/systemcoupling/core/adaptor/api_23_1/apip.py
ansys/systemcoupling/core/adaptor/api_23_1/ascii_output.py
ansys/systemcoupling/core/adaptor/api_23_1/attribute.py
ansys/systemcoupling/core/adaptor/api_23_1/attribute_child.py
ansys/systemcoupling/core/adaptor/api_23_1/available_ports.py
ansys/systemcoupling/core/adaptor/api_23_1/avoid_data_reconstruction.py
ansys/systemcoupling/core/adaptor/api_23_1/case_root.py
ansys/systemcoupling/core/adaptor/api_23_1/clear_state.py
ansys/systemcoupling/core/adaptor/api_23_1/coupling_interface.py
ansys/systemcoupling/core/adaptor/api_23_1/coupling_interface_child.py
ansys/systemcoupling/core/adaptor/api_23_1/coupling_participant.py
ansys/systemcoupling/core/adaptor/api_23_1/coupling_participant_child.py
ansys/systemcoupling/core/adaptor/api_23_1/create_restart_point.py
ansys/systemcoupling/core/adaptor/api_23_1/data_transfer.py
ansys_systemcoupling_core-0.11.3.dist-info/licenses/LICENSE
ansys_systemcoupling_core-0.11.3.dist-info/WHEEL
ansys_systemcoupling_core-0.11.3.dist-info/METADATA
ansys_systemcoupling_core-0.11.3.dist-info/RECORD
