Metadata-Version: 2.4
Name: ansys-systemcoupling-core
Version: 0.11.3
Summary: A Python wrapper for Ansys System Coupling.
Author-email: "ANSYS, Inc." <pyansys.support@ansys.com>
Maintainer-email: PyAnsys developers <pyansys.maintainers@ansys.com>
Requires-Python: >=3.10,<3.14
Classifier: Development Status :: 4 - Beta
Classifier: Intended Audience :: Science/Research
Classifier: Topic :: Scientific/Engineering :: Information Analysis
Classifier: License :: OSI Approved :: MIT License
Classifier: Operating System :: Microsoft :: Windows
Classifier: Operating System :: POSIX
Classifier: Operating System :: MacOS
Classifier: Programming Language :: Python :: 3.10
Classifier: Programming Language :: Python :: 3.11
Classifier: Programming Language :: Python :: 3.12
Classifier: Programming Language :: Python :: 3.13
License-File: LICENSE
Requires-Dist: ansys-api-systemcoupling==0.2.0
Requires-Dist: ansys-platform-instancemanagement~=1.0
Requires-Dist: docker>=7.1.0
Requires-Dist: grpcio>=1.30.0
Requires-Dist: grpcio-status>=1.30.0
Requires-Dist: googleapis-common-protos>=1.50.0
Requires-Dist: psutil>=5.7.0
Requires-Dist: pyyaml
Requires-Dist: appdirs>=1.4.0
Requires-Dist: importlib-metadata>=4.0
Requires-Dist: matplotlib>=3.8.2
Requires-Dist: build ; extra == "build"
Requires-Dist: black==25.11.0 ; extra == "classesgen"
Requires-Dist: isort==7.0.0 ; extra == "classesgen"
Requires-Dist: ansys-sphinx-theme==1.6.3 ; extra == "doc"
Requires-Dist: jupyter_sphinx==0.5.3 ; extra == "doc"
Requires-Dist: matplotlib ; extra == "doc"
Requires-Dist: numpydoc==1.9.0 ; extra == "doc"
Requires-Dist: pypandoc==1.16.2 ; extra == "doc"
Requires-Dist: pytest-sphinx==0.6.3 ; extra == "doc"
Requires-Dist: sphinx>=8.1.3,<9.0.0 ; extra == "doc"
Requires-Dist: sphinx-autobuild==2024.10.3 ; extra == "doc"
Requires-Dist: sphinx-autodoc-typehints==3.1.0 ; extra == "doc"
Requires-Dist: sphinx-copybutton==0.5.2 ; extra == "doc"
Requires-Dist: sphinx-gallery==0.19.0 ; extra == "doc"
Requires-Dist: sphinx-notfound-page==1.1.0 ; extra == "doc"
Requires-Dist: sphinxcontrib-websupport==2.0.0 ; extra == "doc"
Requires-Dist: sphinxemoji==0.3.1 ; extra == "doc"
Requires-Dist: ansys-fluent-core==0.35.0 ; extra == "doc"
Requires-Dist: ansys-mapdl-core==0.71.1 ; extra == "doc"
Requires-Dist: codespell==2.4.1 ; extra == "style"
Requires-Dist: flake8==7.3.0 ; extra == "style"
Requires-Dist: pytest ; extra == "tests"
Requires-Dist: pytest-cov ; extra == "tests"
Requires-Dist: psutil>=5.7.0 ; extra == "tests"
Project-URL: Documentation, https://systemcoupling.docs.pyansys.com/
Project-URL: Homepage, https://github.com/ansys/pysystem-coupling/
Project-URL: Source, https://github.com/ansys/pysystem-coupling/
Project-URL: Tracker, https://github.com/ansys/pysystem-coupling/issues
Provides-Extra: build
Provides-Extra: classesgen
Provides-Extra: doc
Provides-Extra: style
Provides-Extra: tests
